{
  "title": "DevFest Berlin 2023",
  "description": "Join the community, learn new things!",
  "image": "images/social-share.png",
  "keywords": "event, gdg, gde, devfest, google, programming, android, chrome, polymer, developers, web, cloud, androiddev",
  "dates": "Novemeber 25, 2023",
  "partnershipProposition": "",
  "share": "Share",
  "followOur": "Follow our",
  "followUs": "Follow us",
  "emailUs": "Email us",
  "partnershipResources": "",
  "eventResources": "",
  "buyTicket": "RSVP",
  "viewHighlights": "View Highlights",
  "offlineMessage": "You can still work offline.",
  "cachingComplete": "Caching complete! Future visits will work offline.",
  "newVersionAvailable": "A new version of this app is available.",
  "refresh": "Refresh",
  "position": "Position",
  "country": "Country",
  "time": "Time",
  "faq": "/data/faq.md",
  "coc": "",
  "timezoneOffset": "-180",
  "mySchedule": {
    "title": "My Schedule",
    "browseSession": "Browse sessions"
  },
  "footerRelBlock": [
    {
      "title": "About",
      "links": [
        {
          "name": "GDG",
          "url": "https://developers.google.com/groups/",
          "newTab": true
        },
        {
          "name": "DevFest",
          "url": "https://devfest.withgoogle.com/",
          "newTab": true
        },
        {
          "name": "GDG Berlin",
          "url": "https://developers.google.com/groups/",
          "newTab": true
        },
        {
          "name": "Meet the Team",
          "url": "https://devfest.berlin",
          "newTab": true
        }
      ]
    },
    {
      "title": "Explore Past DevFests",
      "links": [
        {
          "name": "DevFest Berlin 2019",
          "url": "https://2019.devfest-berlin.de/",
          "newTab": true
        }
      ]
    },
    {
      "title": "Event Resources",
      "links": [
        {
          "name": "FAQs",
          "url": "/faq/",
          "newTab": false
        }
      ]
    }
  ],
  "subscribeNote": "No spam, only the latest news and updates!",
  "codeOfConduct": "Code of Conduct",
  "codeOfConductBlock": {
    "organization": "DevFest",
    "form": "https://bit.ly/2RstTJ8",
    "contacts": [
      "Organizer Oleh Zasadnyy, [+38 093 486 6460](tel:+380934866460), o.zasadnyy@gdg.org.ua",
      "Organizer Sofiya Huts, [+38 093 486 1425](tel:+380934861425), s.huts@gdg.org.ua"
    ]
  },
  "aboutBlock": {
    "title": "About",
    "callToAction": {
      "featuredSessions": {
        "description": "GDG DevFest Berlin brings together the world class experts in Android, Web and Cloud technologies to Berlin for the whole day of sessions, workshops and showcases!"
      }
    },
    "statisticsBlock": {
      "attendees": {
        "label": "Attendees",
        "number": "250+"
      },
      "days": {
        "label": "Days",
        "number": "1"
      },
      "sessions": {
        "label": "Sessions",
        "number": "13"
      },
      "tracks": {
        "label": "Tracks",
        "number": "2"
      }
    }
  },
  "ticketsBlock": {
    "title": "Tickets",
    "ticketsDetails": "Join remotely, all you need is access to YouTube",
    "soldOut": "You missed it!",
    "notAvailableYet": "Not available yet",
    "save": "Save ${discount}% today"
  },
  "partnersBlock": {
    "title": "Communities",
    "button": "Become a partner",
    "form": {
      "title": "Become a partner!",
      "submitLabel": "Submit",
      "fullName": "Full Name",
      "companyName": "Company Name"
    },
    "toast": "We will contact you soon!"
  },
  "featuredVideos": {
    "title": "DFUA'16 featured videos",
    "callToAction": {
      "label": "See all videos",
      "link": "https://www.youtube.com/playlist?list=PLt8lEzcLNl31AouwDkbLbLARlQFwNS2en"
    }
  },
  "speakers": {
    "skills": "Skills",
    "previousYears": "Years",
    "previousYear": "Year"
  },
  "speakersBlock": {
    "title": "Speakers",
    "callToAction": {
      "label": "View all speakers",
      "link": "/speakers/"
    }
  },
  "previousSpeakersBlock": {
    "title": "Previous speakers",
    "callToAction": {
      "label": "View all",
      "link": "/previous-speakers/"
    }
  },
  "galleryBlock": {
    "title": "#dfua16 highlights",
    "description": "This year's festival built lots of excitement. Check out photos from featured talks, hands-on learning sessions, and after-hours fun.",
    "callToAction": {
      "label": "See all photos",
      "link": "https://goo.gl/photos/H8s3CtPexCzkLqSt9"
    }
  },
  "mapBlock": {
    "title": "Location"
  },
  "subscribeBlock": {
    "callToAction": {
      "description": "Get notified about the important conference updates",
      "label": "Subscribe"
    },
    "yourEmail": "Your email",
    "emailAddress": "Email Address",
    "firstName": "First Name",
    "lastName": "Last Name",
    "formTitle": "Get the latest updates, insights and news about GDG DevFest Ukraine sent to your inbox.",
    "emailRequired": "Please enter a valid email address.",
    "subscribe": "Subscribe",
    "subscribed": "Subscribed",
    "close": "Close",
    "generalError": "An error has occurred. Please, try again later.",
    "toast": "Successfully subscribed!"
  },
  "team": {
    "description": "DevFest team has never been more diverse! It has united [GDG Berlin](https://gdg.community.dev/gdg-berlin/), [GDG Berlin Android](https://gdg.community.dev/gdg-berlin-android/), [GDG Berlin Golang](https://gdg.community.dev/gdg-berlin-golang/), [GDG Cloud Berlin](https://gdg.community.dev/gdg-cloud-berlin/), [Women TechMakers](https://gdg.community.dev/women-techmakers-berlin/), [Flutter Berlin](https://www.meetup.com/en-US/flutter-berlin/) and [Kotlin User Group Berlin](https://www.meetup.com/en-US/kotlin-berlin/). They are independant groups of tech enthusiasts who create exciting events and share their passion for various technologies."
  },
  "feedback": {
    "save": "Save",
    "headline": "Review session",
    "leaveFeedback": "to leave feedback",
    "feedbackRecorded": "Your saved",
    "feedbackDeleted": "Feedback deleted",
    "helperText": "Comments will be anonymously provided to speakers",
    "somethingWentWrong": "Something went wrong",
    "contentCaption": "Content quality",
    "styleCaption": "Presentation style",
    "deleteFeedback": "Delete",
    "sessionClosed": "Session reviews are not open"
  },
  "sessionDetails": {
    "contentLevel": "Content level",
    "viewPresentation": "View presentation",
    "viewVideo": "View video",
    "speakers": "Speakers"
  },
  "speakerDetails": {
    "sessions": "Sessions"
  },
  "aboutOrganizerBlock": {
    "image": "/images/team.jpg",
    "blocks": [
      {
        "title": "Organizer",
        "description": "Berlin GDGs, Flutter Berlin,  Kotlin User Group, and Women TechMakers have united to create DevFest Berlin 2023. Our mission is to celebrate Berlin’s diverse tech community and provide a platform for learning, networking, and inspiration.",
        "callToAction": {
          "label": "Open team page",
          "link": "/team"
        }
      },
      {
        "title": "What is a GDG?",
        "description": "A Google Developer Group is a community of volunteers who create exciting projects and share experiences about Google technologies.",
        "callToAction": {
          "label": "Read more",
          "link": "https://developers.google.com/groups/",
          "newTab": true
        }
      },
      {
        "title": "What is DevFest?",
        "description": "DevFests are community-led non-profit developer events crafted with love by local tech community event organizers.",
        "callToAction": {
          "label": "Read more",
          "link": "https://devfest.withgoogle.com/",
          "newTab": true
        }
      }
    ]
  },
  "filters": {
    "title": "Filters",
    "results": "Results",
    "tags": "Tags",
    "complexity": "Complexity",
    "clear": "Clear all"
  },
  "addToHomeScreen": {
    "cta": "Add to Home Screen"
  }
}
